threaded_task_executor/__init__.py
threaded_task_executor/queue_peek.py
threaded_task_executor/task.py
threaded_task_executor/task_queue.py
threaded_task_executor-1.1.dist-info/LICENSE
threaded_task_executor-1.1.dist-info/METADATA
threaded_task_executor-1.1.dist-info/WHEEL
threaded_task_executor-1.1.dist-info/top_level.txt
threaded_task_executor-1.1.dist-info/RECORD
