Metadata-Version: 2.1
Name: threaded-task-executor
Version: 1.1
Summary: Spawn a thread that executes tasks in order
Home-page: http://github.com/enchant97/python-threadedtaskexecutor
Author: enchant97
Author-email: contact@enchantedcode.co.uk
License: mit
Keywords: threading tasks order queue
Platform: UNKNOWN
Classifier: Development Status :: 5 - Production/Stable
Classifier: License :: OSI Approved :: MIT License
Classifier: Programming Language :: Python :: 3.5
Classifier: Programming Language :: Python :: 3.6
Classifier: Programming Language :: Python :: 3.7
Classifier: Topic :: Utilities
Requires-Python: >=3.5
